{
  "coord": {
    "lon": -8.5457,
    "lat": 42.8805
  },
  "weather": [
    {
      "id": 801,
      "main": "Clouds",
      "description": "few clouds",
      "icon": "02n"
    }
  ],
  "base": "stations",
  "main": {
    "temp": 6.86,
    "feels_like": 6.18,
    "temp_min": 6.86,
    "temp_max": 8.82,
    "pressure": 1020,
    "humidity": 91,
    "sea_level": 1020,
    "grnd_level": 987
  },
  "visibility": 10000,
  "wind": {
    "speed": 1.41,
    "deg": 31,
    "gust": 1.61
  },
  "clouds": {
    "all": 24
  },
  "dt": 1777085297,
  "sys": {
    "type": 2,
    "id": 2019170,
    "country": "ES",
    "sunrise": 1777095421,
    "sunset": 1777145220
  },
  "timezone": 7200,
  "id": 3109642,
  "name": "Santiago de Compostela",
  "cod": 200,
  "_last_updated_utc": "2026-04-25T02:48:17.378Z"
}